{"cameraMode":{"drawMode":0,"name":"Shaded","section":"Shading Mode"},"sceneLighting":true,"audioPlay":false,"sceneViewState":{"m_AlwaysRefresh":false,"showFog":true,"showSkybox":true,"showFlares":true,"showImageEffects":true,"showParticleSystems":true,"showVisualEffectGraphs":true,"m_FxEnabled":true},"in2DMode":false,"pivot":{"x":14.439532279968262,"y":5.144131660461426,"z":8.782649993896485},"rotation":{"x":-0.04011646285653114,"y":0.9467766880989075,"z":-0.29163798689842226,"w":-0.1302359402179718},"size":7.789827346801758,"orthographic":false}